Workbook

Sheet Telecom Customers
A1: customer_id | B1: gender | C1: age | D1: married | E1: number_of_dependents | F1: city | G1: zip_code | H1: latitude | I1: longitude | J1: number_of_referrals | K1: tenure_in_months | L1: offer | M1: phone_service | N1: avg_monthly_long_distance_charges | O1: multiple_lines | P1: internet_service | Q1: internet_type | R1: avg_monthly_gb_download | S1: online_security | T1: online_backup | U1: device_protection_plan | V1: premium_tech_support | W1: streaming_tv | X1: streaming_movies | Y1: streaming_music | Z1: unlimited_data | AA1: contract | AB1: paperless_billing | AC1: payment_method | AD1: monthly_charge | AE1: total_charges | AF1: total_refunds | AG1: total_extra_data_charges | AH1: total_long_distance_charges | AI1: total_revenue | AJ1: customer_status | AK1: churn_category | AL1: churn_reason | AM1: multiple_lines__ | AN1: online_security_
A2: 0002-ORFBO | B2: Female | C2: 37 | D2: Yes | E2: 0 | F2: Frazier Park | G2: 93225 | H2: 34.827662 | I2: -118.99907 | J2: 2 | K2: 9 | L2: 0 | M2: Yes | N2: 42.39 | O2: No | P2: Yes | Q2: Cable | R2: 16 | S2: No | T2: Yes | U2: No | V2: Yes | W2: Yes | X2: No | Y2: No | Z2: Yes | AA2: One Year | AB2: Yes | AC2: Credit Card | AD2: 65.6 | AE2: 593.3 | AF2: 0 | AG2: 0 | AH2: 381.51 | AI2: 974.81 | AJ2: Stayed | AK2: 0 | AL2: 0 | AM2: No | AN2: No
A3: 0003-MKNFE | B3: Male | C3: 46 | D3: No | E3: 0 | F3: Glendale | G3: 91206 | H3: 34.162515 | I3: -118.20387 | J3: 0 | K3: 9 | L3: 0 | M3: Yes | N3: 10.69 | O3: Yes | P3: Yes | Q3: Cable | R3: 10 | S3: No | T3: No | U3: No | V3: No | W3: No | X3: Yes | Y3: Yes | Z3: No | AA3: Month-to-Month | AB3: No | AC3: Credit Card | AD3: -4 | AE3: 542.4 | AF3: 38.33 | AG3: 10 | AH3: 96.21 | AI3: 610.28 | AJ3: Stayed | AK3: 0 | AL3: 0 | AM3: Yes | AN3: No
A4: 0004-TLHLJ | B4: Male | C4: 50 | D4: No | E4: 0 | F4: Costa Mesa | G4: 92627 | H4: 33.645672 | I4: -117.92261 | J4: 0 | K4: 4 | L4: Offer E | M4: Yes | N4: 33.65 | O4: No | P4: Yes | Q4: Fiber Optic | R4: 30 | S4: No | T4: No | U4: Yes | V4: No | W4: No | X4: No | Y4: No | Z4: Yes | AA4: Month-to-Month | AB4: Yes | AC4: Bank Withdrawal | AD4: 73.9 | AE4: 280.85 | AF4: 0 | AG4: 0 | AH4: 134.6 | AI4: 415.45 | AJ4: Churned | AK4: Competitor | AL4: Competitor had better devices | AM4: No | AN4: No
A5: 0011-IGKFF | B5: Male | C5: 78 | D5: Yes | E5: 0 | F5: Martinez | G5: 94553 | H5: 38.014457 | I5: -122.11543 | J5: 1 | K5: 13 | L5: Offer D | M5: Yes | N5: 27.82 | O5: No | P5: Yes | Q5: Fiber Optic | R5: 4 | S5: No | T5: Yes | U5: Yes | V5: No | W5: Yes | X5: Yes | Y5: No | Z5: Yes | AA5: Month-to-Month | AB5: Yes | AC5: Bank Withdrawal | AD5: 98 | AE5: 1237.85 | AF5: 0 | AG5: 0 | AH5: 361.66 | AI5: 1599.51 | AJ5: Churned | AK5: Dissatisfaction | AL5: Product dissatisfaction | AM5: No | AN5: No
A6: 0013-EXCHZ | B6: Female | C6: 75 | D6: Yes | E6: 0 | F6: Camarillo | G6: 93010 | H6: 34.227846 | I6: -119.0799 | J6: 3 | K6: 3 | L6: 0 | M6: Yes | N6: 7.38 | O6: No | P6: Yes | Q6: Fiber Optic | R6: 11 | S6: No | T6: No | U6: No | V6: Yes | W6: Yes | X6: No | Y6: No | Z6: Yes | AA6: Month-to-Month | AB6: Yes | AC6: Credit Card | AD6: 83.9 | AE6: 267.4 | AF6: 0 | AG6: 0 | AH6: 22.14 | AI6: 289.54 | AJ6: Churned | AK6: Dissatisfaction | AL6: Network reliability | AM6: No | AN6: No
A7: 0013-MHZWF | B7: Female | C7: 23 | D7: No | E7: 3 | F7: Midpines | G7: 95345 | H7: 37.581496 | I7: -119.97276 | J7: 0 | K7: 9 | L7: Offer E | M7: Yes | N7: 16.77 | O7: No | P7: Yes | Q7: Cable | R7: 73 | S7: No | T7: No | U7: No | V7: Yes | W7: Yes | X7: Yes | Y7: Yes | Z7: Yes | AA7: Month-to-Month | AB7: Yes | AC7: Credit Card | AD7: 69.4 | AE7: 571.45 | AF7: 0 | AG7: 0 | AH7: 150.93 | AI7: 722.38 | AJ7: Stayed | AK7: 0 | AL7: 0 | AM7: No | AN7: No
A8: 0013-SMEOE | B8: Female | C8: 67 | D8: Yes | E8: 0 | F8: Lompoc | G8: 93437 | H8: 34.757477 | I8: -120.55051 | J8: 1 | K8: 71 | L8: Offer A | M8: Yes | N8: 9.96 | O8: No | P8: Yes | Q8: Fiber Optic | R8: 14 | S8: Yes | T8: Yes | U8: Yes | V8: Yes | W8: Yes | X8: Yes | Y8: Yes | Z8: Yes | AA8: Two Year | AB8: Yes | AC8: Bank Withdrawal | AD8: 109.7 | AE8: 7904.25 | AF8: 0 | AG8: 0 | AH8: 707.16 | AI8: 8611.41 | AJ8: Stayed | AK8: 0 | AL8: 0 | AM8: No | AN8: Yes
A9: 0014-BMAQU | B9: Male | C9: 52 | D9: Yes | E9: 0 | F9: Napa | G9: 94558 | H9: 38.489789 | I9: -122.27011 | J9: 8 | K9: 63 | L9: Offer B | M9: Yes | N9: 12.96 | O9: Yes | P9: Yes | Q9: Fiber Optic | R9: 7 | S9: Yes | T9: No | U9: No | V9: Yes | W9: No | X9: No | Y9: No | Z9: No | AA9: Two Year | AB9: Yes | AC9: Credit Card | AD9: 84.65 | AE9: 5377.8 | AF9: 0 | AG9: 20 | AH9: 816.48 | AI9: 6214.28 | AJ9: Stayed | AK9: 0 | AL9: 0 | AM9: Yes | AN9: Yes
A10: 0015-UOCOJ | B10: Female | C10: 68 | D10: No | E10: 0 | F10: Simi Valley | G10: 93063 | H10: 34.296813 | I10: -118.6857 | J10: 0 | K10: 7 | L10: Offer E | M10: Yes | N10: 10.53 | O10: No | P10: Yes | Q10: DSL | R10: 21 | S10: Yes | T10: No | U10: No | V10: No | W10: No | X10: No | Y10: No | Z10: Yes | AA10: Two Year | AB10: Yes | AC10: Bank Withdrawal | AD10: 48.2 | AE10: 340.35 | AF10: 0 | AG10: 0 | AH10: 73.71 | AI10: 414.06 | AJ10: Stayed | AK10: 0 | AL10: 0 | AM10: No | AN10: Yes
A11: 0016-QLJIS | B11: Female | C11: 43 | D11: Yes | E11: 1 | F11: Sheridan | G11: 95681 | H11: 38.984756 | I11: -121.34507 | J11: 3 | K11: 65 | L11: 0 | M11: Yes | N11: 28.46 | O11: Yes | P11: Yes | Q11: Cable | R11: 14 | S11: Yes | T11: Yes | U11: Yes | V11: Yes | W11: Yes | X11: Yes | Y11: Yes | Z11: Yes | AA11: Two Year | AB11: Yes | AC11: Credit Card | AD11: 90.45 | AE11: 5957.9 | AF11: 0 | AG11: 0 | AH11: 1849.9 | AI11: 7807.8 | AJ11: Stayed | AK11: 0 | AL11: 0 | AM11: Yes | AN11: Yes
A12: 0017-DINOC | B12: Male | C12: 47 | D12: No | E12: 0 | F12: Rancho Santa Fe | G12: 92091 | H12: 32.99356 | I12: -117.20712 | J12: 0 | K12: 54 | L12: 0 | M12: No | N12: 0 | O12: 0 | P12: Yes | Q12: Cable | R12: 10 | S12: Yes | T12: No | U12: No | V12: Yes | W12: Yes | X12: No | Y12: No | Z12: Yes | AA12: Two Year | AB12: No | AC12: Credit Card | AD12: 45.2 | AE12: 2460.55 | AF12: 0 | AG12: 0 | AH12: 0 | AI12: 2460.55 | AJ12: Stayed | AK12: 0 | AL12: 0 | AM12: 0 | AN12: Yes
A13: 0017-IUDMW | B13: Female | C13: 25 | D13: Yes | E13: 2 | F13: Sunnyvale | G13: 94086 | H13: 37.378541 | I13: -122.02046 | J13: 2 | K13: 72 | L13: 0 | M13: Yes | N13: 16.01 | O13: Yes | P13: Yes | Q13: Fiber Optic | R13: 59 | S13: Yes | T13: Yes | U13: Yes | V13: Yes | W13: Yes | X13: Yes | Y13: Yes | Z13: Yes | AA13: Two Year | AB13: Yes | AC13: Credit Card | AD13: 116.8 | AE13: 8456.75 | AF13: 0 | AG13: 0 | AH13: 1152.72 | AI13: 9609.47 | AJ13: Stayed | AK13: 0 | AL13: 0 | AM13: Yes | AN13: Yes
A14: 0018-NYROU | B14: Female | C14: 58 | D14: Yes | E14: 0 | F14: Antelope | G14: 95843 | H14: 38.715498 | I14: -121.36341 | J14: 0 | K14: 5 | L14: 0 | M14: Yes | N14: 18.65 | O14: No | P14: Yes | Q14: Fiber Optic | R14: 10 | S14: No | T14: No | U14: No | V14: No | W14: No | X14: No | Y14: No | Z14: Yes | AA14: Month-to-Month | AB14: Yes | AC14: Bank Withdrawal | AD14: 68.95 | AE14: 351.5 | AF14: 0 | AG14: 0 | AH14: 93.25 | AI14: 444.75 | AJ14: Stayed | AK14: 0 | AL14: 0 | AM14: No | AN14: No
A15: 0019-EFAEP | B15: Female | C15: 32 | D15: No | E15: 0 | F15: La Mesa | G15: 91942 | H15: 32.782501 | I15: -117.01611 | J15: 0 | K15: 72 | L15: Offer A | M15: Yes | N15: 2.25 | O15: Yes | P15: Yes | Q15: Fiber Optic | R15: 16 | S15: Yes | T15: Yes | U15: Yes | V15: No | W15: Yes | X15: No | Y15: No | Z15: Yes | AA15: Two Year | AB15: Yes | AC15: Bank Withdrawal | AD15: 101.3 | AE15: 7261.25 | AF15: 0 | AG15: 0 | AH15: 162 | AI15: 7423.25 | AJ15: Stayed | AK15: 0 | AL15: 0 | AM15: Yes | AN15: Yes
A16: 0019-GFNTW | B16: Female | C16: 39 | D16: No | E16: 0 | F16: Los Olivos | G16: 93441 | H16: 34.70434 | I16: -120.02609 | J16: 0 | K16: 56 | L16: 0 | M16: No | N16: 0 | O16: 0 | P16: Yes | Q16: DSL | R16: 19 | S16: Yes | T16: Yes | U16: Yes | V16: Yes | W16: No | X16: No | Y16: No | Z16: Yes | AA16: Two Year | AB16: No | AC16: Bank Withdrawal | AD16: 45.05 | AE16: 2560.1 | AF16: 0 | AG16: 0 | AH16: 0 | AI16: 2560.1 | AJ16: Stayed | AK16: 0 | AL16: 0 | AM16: 0 | AN16: Yes
A17: 0020-INWCK | B17: Female | C17: 58 | D17: Yes | E17: 2 | F17: Woodlake | G17: 93286 | H17: 36.464635 | I17: -119.09435 | J17: 9 | K17: 71 | L17: Offer A | M17: Yes | N17: 27.26 | O17: Yes | P17: Yes | Q17: Fiber Optic | R17: 12 | S17: No | T17: Yes | U17: Yes | V17: No | W17: No | X17: Yes | Y17: Yes | Z17: Yes | AA17: Two Year | AB17: Yes | AC17: Credit Card | AD17: 95.75 | AE17: 6849.4 | AF17: 0 | AG17: 0 | AH17: 1935.46 | AI17: 8784.86 | AJ17: Stayed | AK17: 0 | AL17: 0 | AM17: Yes | AN17: No
A18: 0020-JDNXP | B18: Female | C18: 52 | D18: Yes | E18: 1 | F18: Point Reyes Station | G18: 94956 | H18: 38.060264 | I18: -122.83065 | J18: 0 | K18: 34 | L18: 0 | M18: No | N18: 0 | O18: 0 | P18: Yes | Q18: DSL | R18: 20 | S18: Yes | T18: No | U18: Yes | V18: Yes | W18: Yes | X18: Yes | Y18: Yes | Z18: Yes | AA18: One Year | AB18: No | AC18: Credit Card | AD18: 61.25 | AE18: 1993.2 | AF18: 0 | AG18: 0 | AH18: 0 | AI18: 1993.2 | AJ18: Stayed | AK18: 0 | AL18: 0 | AM18: 0 | AN18: Yes
A19: 0021-IKXGC | B19: Female | C19: 72 | D19: No | E19: 0 | F19: San Marcos | G19: 92078 | H19: 33.119028 | I19: -117.16604 | J19: 0 | K19: 1 | L19: Offer E | M19: Yes | N19: 7.77 | O19: Yes | P19: Yes | Q19: Fiber Optic | R19: 22 | S19: No | T19: No | U19: No | V19: No | W19: No | X19: No | Y19: No | Z19: Yes | AA19: One Year | AB19: Yes | AC19: Bank Withdrawal | AD19: 72.1 | AE19: 72.1 | AF19: 0 | AG19: 0 | AH19: 7.77 | AI19: 79.87 | AJ19: Joined | AK19: 0 | AL19: 0 | AM19: Yes | AN19: No
A20: 0022-TCJCI | B20: Male | C20: 79 | D20: No | E20: 0 | F20: Daly City | G20: 94015 | H20: 37.680844 | I20: -122.48131 | J20: 0 | K20: 45 | L20: 0 | M20: Yes | N20: 10.67 | O20: No | P20: Yes | Q20: DSL | R20: 17 | S20: Yes | T20: No | U20: Yes | V20: No | W20: No | X20: Yes | Y20: No | Z20: Yes | AA20: One Year | AB20: No | AC20: Credit Card | AD20: 62.7 | AE20: 2791.5 | AF20: 0 | AG20: 0 | AH20: 480.15 | AI20: 3271.65 | AJ20: Churned | AK20: Dissatisfaction | AL20: Limited range of services | AM20: No | AN20: Yes
A21: 0023-HGHWL | B21: Male | C21: 67 | D21: No | E21: 0 | F21: Morgan Hill | G21: 95037 | H21: 37.161544 | I21: -121.64937 | J21: 0 | K21: 1 | L21: 0 | M21: No | N21: 0 | O21: 0 | P21: Yes | Q21: Cable | R21: 9 | S21: No | T21: No | U21: No | V21: No | W21: No | X21: No | Y21: No | Z21: Yes | AA21: Month-to-Month | AB21: Yes | AC21: Bank Withdrawal | AD21: 25.1 | AE21: 25.1 | AF21: 0 | AG21: 0 | AH21: 0 | AI21: 25.1 | AJ21: Churned | AK21: Competitor | AL21: Competitor made better offer | AM21: 0 | AN21: No
A22: 0023-UYUPN | B22: Female | C22: 79 | D22: Yes | E22: 0 | F22: Ahwahnee | G22: 93601 | H22: 37.375816 | I22: -119.73994 | J22: 0 | K22: 50 | L22: 0 | M22: Yes | N22: 31.43 | O22: Yes | P22: No | Q22: 0 | R22: 0 | S22: 0 | T22: 0 | U22: 0 | V22: 0 | W22: 0 | X22: 0 | Y22: 0 | Z22: 0 | AA22: One Year | AB22: No | AC22: Bank Withdrawal | AD22: 25.2 | AE22: 1306.3 | AF22: 0 | AG22: 0 | AH22: 1571.5 | AI22: 2877.8 | AJ22: Stayed | AK22: 0 | AL22: 0 | AM22: Yes | AN22: 0
A23: 0023-XUOPT | B23: Female | C23: 26 | D23: Yes | E23: 0 | F23: Carnelian Bay | G23: 96140 | H23: 39.227434 | I23: -120.09181 | J23: 1 | K23: 13 | L23: 0 | M23: Yes | N23: 43.56 | O23: Yes | P23: Yes | Q23: Fiber Optic | R23: 52 | S23: No | T23: Yes | U23: Yes | V23: No | W23: Yes | X23: No | Y23: No | Z23: Yes | AA23: Month-to-Month | AB23: No | AC23: Bank Withdrawal | AD23: 94.1 | AE23: 1215.6 | AF23: 0 | AG23: 0 | AH23: 566.28 | AI23: 1781.88 | AJ23: Churned | AK23: Other | AL23: Don't know | AM23: Yes | AN23: No
A24: 0027-KWYKW | B24: Female | C24: 30 | D24: Yes | E24: 2 | F24: Alpaugh | G24: 93201 | H24: 35.869626 | I24: -119.49877 | J24: 1 | K24: 23 | L24: Offer D | M24: Yes | N24: 34.91 | O24: Yes | P24: Yes | Q24: Fiber Optic | R24: 30 | S24: No | T24: No | U24: No | V24: No | W24: Yes | X24: No | Y24: No | Z24: Yes | AA24: Month-to-Month | AB24: Yes | AC24: Bank Withdrawal | AD24: 83.75 | AE24: 1849.95 | AF24: 0 | AG24: 0 | AH24: 802.93 | AI24: 2652.88 | AJ24: Stayed | AK24: 0 | AL24: 0 | AM24: Yes | AN24: No
A25: 0030-FNXPP | B25: Female | C25: 22 | D25: No | E25: 0 | F25: Keeler | G25: 93530 | H25: 36.560498 | I25: -117.96246 | J25: 0 | K25: 3 | L25: 0 | M25: Yes | N25: 3.12 | O25: No | P25: No | Q25: 0 | R25: 0 | S25: 0 | T25: 0 | U25: 0 | V25: 0 | W25: 0 | X25: 0 | Y25: 0 | Z25: 0 | AA25: Month-to-Month | AB25: No | AC25: Credit Card | AD25: 19.85 | AE25: 57.2 | AF25: 0 | AG25: 0 | AH25: 9.36 | AI25: 66.56 | AJ25: Joined | AK25: 0 | AL25: 0 | AM25: No | AN25: 0
A26: 0031-PVLZI | B26: Female | C26: 34 | D26: Yes | E26: 0 | F26: Korbel | G26: 95550 | H26: 40.7666 | I26: -123.80458 | J26: 0 | K26: 4 | L26: Offer E | M26: Yes | N26: 12.43 | O26: No | P26: No | Q26: 0 | R26: 0 | S26: 0 | T26: 0 | U26: 0 | V26: 0 | W26: 0 | X26: 0 | Y26: 0 | Z26: 0 | AA26: Month-to-Month | AB26: No | AC26: Credit Card | AD26: 20.35 | AE26: 76.35 | AF26: 0 | AG26: 0 | AH26: 49.72 | AI26: 126.07 | AJ26: Churned | AK26: Price | AL26: Long distance charges | AM26: No | AN26: 0
A27: 0032-PGELS | B27: Female | C27: 37 | D27: Yes | E27: 1 | F27: Palomar Mountain | G27: 92060 | H27: 33.309852 | I27: -116.82309 | J27: 1 | K27: 1 | L27: 0 | M27: No | N27: 0 | O27: 0 | P27: Yes | Q27: DSL | R27: 19 | S27: Yes | T27: No | U27: No | V27: No | W27: No | X27: No | Y27: No | Z27: Yes | AA27: Month-to-Month | AB27: No | AC27: Bank Withdrawal | AD27: 30.5 | AE27: 30.5 | AF27: 0 | AG27: 0 | AH27: 0 | AI27: 30.5 | AJ27: Churned | AK27: Attitude | AL27: Attitude of service provider | AM27: 0 | AN27: Yes
A28: 0036-IHMOT | B28: Female | C28: 37 | D28: Yes | E28: 3 | F28: Parlier | G28: 93648 | H28: 36.622237 | I28: -119.52113 | J28: 10 | K28: 55 | L28: 0 | M28: Yes | N28: 35.04 | O28: No | P28: Yes | Q28: Fiber Optic | R28: 57 | S28: No | T28: Yes | U28: Yes | V28: Yes | W28: Yes | X28: Yes | Y28: Yes | Z28: No | AA28: One Year | AB28: Yes | AC28: Bank Withdrawal | AD28: 103.7 | AE28: 5656.75 | AF28: 0 | AG28: 20 | AH28: 1927.2 | AI28: 7603.95 | AJ28: Stayed | AK28: 0 | AL28: 0 | AM28: No | AN28: No
A29: 0040-HALCW | B29: Male | C29: 42 | D29: Yes | E29: 3 | F29: Modesto | G29: 95358 | H29: 37.612612 | I29: -121.10857 | J29: 3 | K29: 54 | L29: 0 | M29: Yes | N29: 19.7 | O29: No | P29: No | Q29: 0 | R29: 0 | S29: 0 | T29: 0 | U29: 0 | V29: 0 | W29: 0 | X29: 0 | Y29: 0 | Z29: 0 | AA29: Two Year | AB29: No | AC29: Credit Card | AD29: 20.4 | AE29: 1090.6 | AF29: 0 | AG29: 0 | AH29: 1063.8 | AI29: 2154.4 | AJ29: Stayed | AK29: 0 | AL29: 0 | AM29: No | AN29: 0
A30: 0042-JVWOJ | B30: Male | C30: 64 | D30: No | E30: 0 | F30: Glen Ellen | G30: 95442 | H30: 38.368744 | I30: -122.52264 | J30: 0 | K30: 26 | L30: Offer C | M30: Yes | N30: 37.7 | O30: No | P30: No | Q30: 0 | R30: 0 | S30: 0 | T30: 0 | U30: 0 | V30: 0 | W30: 0 | X30: 0 | Y30: 0 | Z30: 0 | AA30: One Year | AB30: Yes | AC30: Bank Withdrawal | AD30: 19.6 | AE30: 471.85 | AF30: 21.25 | AG30: 0 | AH30: 980.2 | AI30: 1430.8 | AJ30: Stayed | AK30: 0 | AL30: 0 | AM30: No | AN30: 0
A31: 0042-RLHYP | B31: Female | C31: 47 | D31: Yes | E31: 3 | F31: Eureka | G31: 95503 | H31: 40.737431 | I31: -124.1089 | J31: 5 | K31: 69 | L31: 0 | M31: Yes | N31: 38.39 | O31: No | P31: No | Q31: 0 | R31: 0 | S31: 0 | T31: 0 | U31: 0 | V31: 0 | W31: 0 | X31: 0 | Y31: 0 | Z31: 0 | AA31: Two Year | AB31: No | AC31: Bank Withdrawal | AD31: 19.7 | AE31: 1396.9 | AF31: 0 | AG31: 0 | AH31: 2648.91 | AI31: 4045.81 | AJ31: Stayed | AK31: 0 | AL31: 0 | AM31: No | AN31: 0
A32: 0048-LUMLS | B32: Male | C32: 23 | D32: Yes | E32: 3 | F32: Moss Beach | G32: 94038 | H32: 37.515556 | I32: -122.50231 | J32: 1 | K32: 37 | L32: Offer C | M32: Yes | N32: 43.01 | O32: No | P32: Yes | Q32: Fiber Optic | R32: 51 | S32: No | T32: No | U32: No | V32: No | W32: Yes | X32: Yes | Y32: Yes | Z32: Yes | AA32: One Year | AB32: No | AC32: Credit Card | AD32: 91.2 | AE32: 3247.55 | AF32: 0 | AG32: 0 | AH32: 1591.37 | AI32: 4838.92 | AJ32: Stayed | AK32: 0 | AL32: 0 | AM32: No | AN32: No
A33: 0048-PIHNL | B33: Female | C33: 48 | D33: Yes | E33: 0 | F33: Los Angeles | G33: 90058 | H33: 34.001617 | I33: -118.22227 | J33: 5 | K33: 49 | L33: Offer B | M33: Yes | N33: 49.58 | O33: No | P33: No | Q33: 0 | R33: 0 | S33: 0 | T33: 0 | U33: 0 | V33: 0 | W33: 0 | X33: 0 | Y33: 0 | Z33: 0 | AA33: One Year | AB33: No | AC33: Bank Withdrawal | AD33: 20.45 | AE33: 900.9 | AF33: 0 | AG33: 0 | AH33: 2429.42 | AI33: 3330.32 | AJ33: Stayed | AK33: 0 | AL33: 0 | AM33: No | AN33: 0
A34: 0052-DCKON | B34: Male | C34: 28 | D34: Yes | E34: 0 | F34: Los Angeles | G34: 90063 | H34: 34.044271 | I34: -118.18524 | J34: 9 | K34: 66 | L34: 0 | M34: Yes | N34: 43.77 | O34: Yes | P34: Yes | Q34: Fiber Optic | R34: 41 | S34: Yes | T34: Yes | U34: Yes | V34: Yes | W34: Yes | X34: Yes | Y34: Yes | Z34: Yes | AA34: One Year | AB34: No | AC34: Bank Withdrawal | AD34: -2 | AE34: 7942.15 | AF34: 0 | AG34: 0 | AH34: 2888.82 | AI34: 10830.97 | AJ34: Stayed | AK34: 0 | AL34: 0 | AM34: Yes | AN34: Yes
A35: 0052-YNYOT | B35: Female | C35: 28 | D35: No | E35: 0 | F35: Calexico | G35: 92231 | H35: 32.690654 | I35: -115.43122 | J35: 0 | K35: 67 | L35: 0 | M35: Yes | N35: 23.12 | O35: No | P35: No | Q35: 0 | R35: 0 | S35: 0 | T35: 0 | U35: 0 | V35: 0 | W35: 0 | X35: 0 | Y35: 0 | Z35: 0 | AA35: One Year | AB35: No | AC35: Bank Withdrawal | AD35: 20.55 | AE35: 1343.4 | AF35: 30.53 | AG35: 0 | AH35: 1549.04 | AI35: 2861.91 | AJ35: Stayed | AK35: 0 | AL35: 0 | AM35: No | AN35: 0
A36: 0056-EPFBG | B36: Male | C36: 33 | D36: Yes | E36: 1 | F36: Redding | G36: 96003 | H36: 40.677649 | I36: -122.29467 | J36: 4 | K36: 20 | L36: 0 | M36: No | N36: 0 | O36: 0 | P36: Yes | Q36: Cable | R36: 22 | S36: Yes | T36: No | U36: Yes | V36: Yes | W36: No | X36: No | Y36: No | Z36: Yes | AA36: Two Year | AB36: Yes | AC36: Credit Card | AD36: 39.4 | AE36: 825.4 | AF36: 0 | AG36: 0 | AH36: 0 | AI36: 825.4 | AJ36: Stayed | AK36: 0 | AL36: 0 | AM36: 0 | AN36: Yes
A37: 0057-QBUQH | B37: Female | C37: 31 | D37: No | E37: 3 | F37: San Martin | G37: 95046 | H37: 37.084697 | I37: -121.60642 | J37: 0 | K37: 43 | L37: 0 | M37: Yes | N37: 30.64 | O37: Yes | P37: No | Q37: 0 | R37: 0 | S37: 0 | T37: 0 | U37: 0 | V37: 0 | W37: 0 | X37: 0 | Y37: 0 | Z37: 0 | AA37: Two Year | AB37: Yes | AC37: Bank Withdrawal | AD37: 25.1 | AE37: 1070.15 | AF37: 0 | AG37: 0 | AH37: 1317.52 | AI37: 2387.67 | AJ37: Stayed | AK37: 0 | AL37: 0 | AM37: Yes | AN37: 0
A38: 0058-EVZWM | B38: Female | C38: 37 | D38: Yes | E38: 0 | F38: Stockton | G38: 95209 | H38: 38.044523 | I38: -121.34805 | J38: 2 | K38: 55 | L38: Offer B | M38: Yes | N38: 5.08 | O38: Yes | P38: Yes | Q38: Fiber Optic | R38: 9 | S38: Yes | T38: No | U38: No | V38: No | W38: Yes | X38: No | Y38: No | Z38: Yes | AA38: Month-to-Month | AB38: Yes | AC38: Bank Withdrawal | AD38: 89.8 | AE38: 4959.6 | AF38: 0 | AG38: 0 | AH38: 279.4 | AI38: 5239 | AJ38: Stayed | AK38: 0 | AL38: 0 | AM38: Yes | AN38: Yes
A39: 0060-FUALY | B39: Female | C39: 60 | D39: Yes | E39: 0 | F39: Los Angeles | G39: 90003 | H39: 33.964131 | I39: -118.27278 | J39: 4 | K39: 59 | L39: Offer B | M39: Yes | N39: 16.39 | O39: Yes | P39: Yes | Q39: Fiber Optic | R39: 14 | S39: Yes | T39: Yes | U39: No | V39: No | W39: Yes | X39: No | Y39: No | Z39: Yes | AA39: Month-to-Month | AB39: Yes | AC39: Bank Withdrawal | AD39: 94.75 | AE39: 5597.65 | AF39: 0 | AG39: 0 | AH39: 967.01 | AI39: 6564.66 | AJ39: Stayed | AK39: 0 | AL39: 0 | AM39: Yes | AN39: Yes
A40: 0064-SUDOG | B40: Female | C40: 48 | D40: Yes | E40: 3 | F40: Huntington Park | G40: 90255 | H40: 33.97803 | I40: -118.21714 | J40: 3 | K40: 12 | L40: 0 | M40: Yes | N40: 19.28 | O40: No | P40: No | Q40: 0 | R40: 0 | S40: 0 | T40: 0 | U40: 0 | V40: 0 | W40: 0 | X40: 0 | Y40: 0 | Z40: 0 | AA40: Two Year | AB40: No | AC40: Bank Withdrawal | AD40: 20.3 | AE40: 224.5 | AF40: 0 | AG40: 0 | AH40: 231.36 | AI40: 455.86 | AJ40: Stayed | AK40: 0 | AL40: 0 | AM40: No | AN40: 0
A41: 0064-YIJGF | B41: Male | C41: 60 | D41: Yes | E41: 3 | F41: Yermo | G41: 92398 | H41: 35.013299 | I41: -116.83409 | J41: 7 | K41: 27 | L41: Offer C | M41: Yes | N41: 25.26 | O41: Yes | P41: Yes | Q41: Fiber Optic | R41: 23 | S41: No | T41: No | U41: No | V41: No | W41: No | X41: No | Y41: No | Z41: Yes | AA41: Month-to-Month | AB41: Yes | AC41: Bank Withdrawal | AD41: 75.75 | AE41: 1929 | AF41: 0 | AG41: 0 | AH41: 682.02 | AI41: 2611.02 | AJ41: Stayed | AK41: 0 | AL41: 0 | AM41: Yes | AN41: No
A42: 0067-DKWBL | B42: Male | C42: 69 | D42: No | E42: 0 | F42: San Diego | G42: 92129 | H42: 32.961064 | I42: -117.13492 | J42: 0 | K42: 2 | L42: 0 | M42: Yes | N42: 43.99 | O42: No | P42: Yes | Q42: DSL | R42: 27 | S42: Yes | T42: No | U42: No | V42: No | W42: No | X42: No | Y42: No | Z42: Yes | AA42: Month-to-Month | AB42: Yes | AC42: Bank Withdrawal | AD42: 49.25 | AE42: 91.1 | AF42: 0 | AG42: 0 | AH42: 87.98 | AI42: 179.08 | AJ42: Churned | AK42: Competitor | AL42: Competitor made better offer | AM42: No | AN42: Yes
A43: 0068-FIGTF | B43: Female | C43: 20 | D43: No | E43: 0 | F43: Fremont | G43: 94539 | H43: 37.516791 | I43: -121.89912 | J43: 0 | K43: 27 | L43: Offer C | M43: Yes | N43: 48.91 | O43: No | P43: Yes | Q43: DSL | R43: 59 | S43: No | T43: Yes | U43: Yes | V43: Yes | W43: Yes | X43: Yes | Y43: Yes | Z43: Yes | AA43: One Year | AB43: No | AC43: Credit Card | AD43: 78.2 | AE43: 2078.95 | AF43: 0 | AG43: 0 | AH43: 1320.57 | AI43: 3399.52 | AJ43: Stayed | AK43: 0 | AL43: 0 | AM43: No | AN43: No
A44: 0071-NDAFP | B44: Male | C44: 31 | D44: Yes | E44: 3 | F44: Santa Rosa | G44: 95405 | H44: 38.439696 | I44: -122.66882 | J44: 1 | K44: 25 | L44: 0 | M44: Yes | N44: 23.69 | O44: Yes | P44: No | Q44: 0 | R44: 0 | S44: 0 | T44: 0 | U44: 0 | V44: 0 | W44: 0 | X44: 0 | Y44: 0 | Z44: 0 | AA44: Two Year | AB44: No | AC44: Credit Card | AD44: 25.5 | AE44: 630.6 | AF44: 44.42 | AG44: 0 | AH44: 592.25 | AI44: 1178.43 | AJ44: Stayed | AK44: 0 | AL44: 0 | AM44: Yes | AN44: 0
A45: 0074-HDKDG | B45: Male | C45: 46 | D45: Yes | E45: 0 | F45: San Jose | G45: 95126 | H45: 37.327069 | I45: -121.91682 | J45: 5 | K45: 25 | L45: 0 | M45: Yes | N45: 6.45 | O45: No | P45: Yes | Q45: Cable | R45: 19 | S45: Yes | T45: Yes | U45: Yes | V45: No | W45: No | X45: No | Y45: No | Z45: Yes | AA45: One Year | AB45: Yes | AC45: Bank Withdrawal | AD45: 61.6 | AE45: 1611 | AF45: 44.9 | AG45: 0 | AH45: 161.25 | AI45: 1727.35 | AJ45: Stayed | AK45: 0 | AL45: 0 | AM45: No | AN45: Yes
A46: 0076-LVEPS | B46: Male | C46: 57 | D46: No | E46: 1 | F46: Tujunga | G46: 91042 | H46: 34.296574 | I46: -118.24484 | J46: 0 | K46: 29 | L46: 0 | M46: No | N46: 0 | O46: 0 | P46: Yes | Q46: DSL | R46: 21 | S46: Yes | T46: Yes | U46: Yes | V46: Yes | W46: No | X46: No | Y46: No | Z46: Yes | AA46: Month-to-Month | AB46: Yes | AC46: Credit Card | AD46: 45 | AE46: 1242.45 | AF46: 12.26 | AG46: 0 | AH46: 0 | AI46: 1230.19 | AJ46: Stayed | AK46: 0 | AL46: 0 | AM46: 0 | AN46: Yes
A47: 0078-XZMHT | B47: Male | C47: 19 | D47: Yes | E47: 0 | F47: Visalia | G47: 93291 | H47: 36.391777 | I47: -119.37284 | J47: 5 | K47: 72 | L47: 0 | M47: Yes | N47: 32.36 | O47: Yes | P47: Yes | Q47: DSL | R47: 52 | S47: No | T47: Yes | U47: Yes | V47: Yes | W47: Yes | X47: Yes | Y47: Yes | Z47: Yes | AA47: Two Year | AB47: Yes | AC47: Bank Withdrawal | AD47: 85.15 | AE47: 6316.2 | AF47: 0 | AG47: 0 | AH47: 2329.92 | AI47: 8646.12 | AJ47: Stayed | AK47: 0 | AL47: 0 | AM47: Yes | AN47: No
A48: 0080-EMYVY | B48: Female | C48: 64 | D48: No | E48: 0 | F48: Lodi | G48: 95240 | H48: 38.123544 | I48: -121.15908 | J48: 0 | K48: 14 | L48: 0 | M48: Yes | N48: 24.04 | O48: No | P48: Yes | Q48: Cable | R48: 12 | S48: No | T48: Yes | U48: No | V48: No | W48: No | X48: No | Y48: No | Z48: Yes | AA48: One Year | AB48: No | AC48: Credit Card | AD48: 51.45 | AE48: 727.85 | AF48: 0 | AG48: 0 | AH48: 336.56 | AI48: 1064.41 | AJ48: Stayed | AK48: 0 | AL48: 0 | AM48: No | AN48: No
A49: 0080-OROZO | B49: Female | C49: 38 | D49: No | E49: 0 | F49: El Portal | G49: 95318 | H49: 37.654551 | I49: -119.82298 | J49: 0 | K49: 35 | L49: Offer C | M49: Yes | N49: 36.42 | O49: No | P49: Yes | Q49: Fiber Optic | R49: 2 | S49: No | T49: No | U49: Yes | V49: Yes | W49: Yes | X49: Yes | Y49: Yes | Z49: Yes | AA49: One Year | AB49: Yes | AC49: Bank Withdrawal | AD49: 99.25 | AE49: 3532 | AF49: 0 | AG49: 0 | AH49: 1274.7 | AI49: 4806.7 | AJ49: Stayed | AK49: 0 | AL49: 0 | AM49: No | AN49: No
A50: 0082-LDZUE | B50: Male | C50: 54 | D50: No | E50: 0 | F50: Calistoga | G50: 94515 | H50: 38.629618 | I50: -122.59322 | J50: 0 | K50: 1 | L50: Offer E | M50: Yes | N50: 42.95 | O50: No | P50: Yes | Q50: DSL | R50: 9 | S50: No | T50: No | U50: No | V50: No | W50: No | X50: No | Y50: No | Z50: Yes | AA50: Month-to-Month | AB50: Yes | AC50: Credit Card | AD50: 44.3 | AE50: 44.3 | AF50: 0 | AG50: 0 | AH50: 42.95 | AI50: 87.25 | AJ50: Joined | AK50: 0 | AL50: 0 | AM50: No | AN50: No
A51: 0082-OQIQY | B51: Male | C51: 50 | D51: No | E51: 0 | F51: Farmington | G51: 95230 | H51: 37.956963 | I51: -120.86306 | J51: 0 | K51: 29 | L51: 0 | M51: Yes | N51: 2.05 | O51: No | P51: Yes | Q51: Fiber Optic | R51: 17 | S51: No | T51: No | U51: No | V51: Yes | W51: Yes | X51: Yes | Y51: Yes | Z51: No | AA51: Month-to-Month | AB51: Yes | AC51: Bank Withdrawal | AD51: 94.2 | AE51: 2607.6 | AF51: 0 | AG51: 20 | AH51: 59.45 | AI51: 2687.05 | AJ51: Stayed | AK51: 0 | AL51: 0 | AM51: No | AN51: No
A52: 0083-PIVIK | B52: Male | C52: 25 | D52: No | E52: 0 | F52: Tulelake | G52: 96134 | H52: 41.813521 | I52: -121.49267 | J52: 0 | K52: 64 | L52: 0 | M52: Yes | N52: 5.49 | O52: Yes | P52: Yes | Q52: DSL | R52: 69 | S52: Yes | T52: Yes | U52: Yes | V52: Yes | W52: Yes | X52: No | Y52: No | Z52: No | AA52: One Year | AB52: No | AC52: Bank Withdrawal | AD52: 81.25 | AE52: 5567.55 | AF52: 0 | AG52: 40 | AH52: 351.36 | AI52: 5958.91 | AJ52: Stayed | AK52: 0 | AL52: 0 | AM52: Yes | AN52: Yes
A53: 0089-IIQKO | B53: Female | C53: 35 | D53: Yes | E53: 3 | F53: Coleville | G53: 96107 | H53: 38.42528 | I53: -119.47574 | J53: 1 | K53: 39 | L53: 0 | M53: Yes | N53: 24.38 | O53: Yes | P53: Yes | Q53: Fiber Optic | R53: 53 | S53: No | T53: No | U53: No | V53: Yes | W53: Yes | X53: Yes | Y53: Yes | Z53: Yes | AA53: Month-to-Month | AB53: Yes | AC53: Credit Card | AD53: 99.95 | AE53: 3767.4 | AF53: 0 | AG53: 0 | AH53: 950.82 | AI53: 4718.22 | AJ53: Stayed | AK53: 0 | AL53: 0 | AM53: Yes | AN53: No
A54: 0093-EXYQL | B54: Female | C54: 72 | D54: No | E54: 0 | F54: Ojai | G54: 93023 | H54: 34.581308 | I54: -118.93195 | J54: 0 | K54: 40 | L54: 0 | M54: Yes | N54: 44.14 | O54: No | P54: Yes | Q54: Fiber Optic | R54: 23 | S54: No | T54: No | U54: No | V54: No | W54: Yes | X54: Yes | Y54: No | Z54: Yes | AA54: Two Year | AB54: Yes | AC54: Bank Withdrawal | AD54: 91.55 | AE54: 3673.6 | AF54: 0 | AG54: 0 | AH54: 1765.6 | AI54: 5439.2 | AJ54: Stayed | AK54: 0 | AL54: 0 | AM54: No | AN54: No
A55: 0093-XWZFY | B55: Male | C55: 51 | D55: No | E55: 0 | F55: Desert Hot Springs | G55: 92241 | H55: 33.832799 | I55: -116.25097 | J55: 0 | K55: 40 | L55: 0 | M55: Yes | N55: 37.69 | O55: Yes | P55: Yes | Q55: Fiber Optic | R55: 15 | S55: No | T55: Yes | U55: Yes | V55: No | W55: Yes | X55: Yes | Y55: Yes | Z55: Yes | AA55: Month-to-Month | AB55: Yes | AC55: Credit Card | AD55: 104.5 | AE55: 4036.85 | AF55: 0 | AG55: 0 | AH55: 1507.6 | AI55: 5544.45 | AJ55: Churned | AK55: Competitor | AL55: Competitor had better devices | AM55: Yes | AN55: No
A56: 0094-OIFMO | B56: Female | C56: 78 | D56: No | E56: 1 | F56: North Hollywood | G56: 91605 | H56: 34.207295 | I56: -118.40002 | J56: 0 | K56: 11 | L56: Offer D | M56: Yes | N56: 11.59 | O56: No | P56: Yes | Q56: Fiber Optic | R56: 29 | S56: No | T56: Yes | U56: No | V56: No | W56: Yes | X56: Yes | Y56: No | Z56: No | AA56: Month-to-Month | AB56: Yes | AC56: Bank Withdrawal | AD56: 95 | AE56: 1120.3 | AF56: 0 | AG56: 120 | AH56: 127.49 | AI56: 1367.79 | AJ56: Churned | AK56: Dissatisfaction | AL56: Product dissatisfaction | AM56: No | AN56: No
A57: 0096-BXERS | B57: Female | C57: 30 | D57: Yes | E57: 0 | F57: Inverness | G57: 94937 | H57: 38.099323 | I57: -122.94572 | J57: 10 | K57: 6 | L57: Offer E | M57: Yes | N57: 42.66 | O57: Yes | P57: Yes | Q57: Cable | R57: 85 | S57: No | T57: No | U57: No | V57: No | W57: No | X57: No | Y57: No | Z57: Yes | AA57: Month-to-Month | AB57: No | AC57: Bank Withdrawal | AD57: 50.35 | AE57: 314.55 | AF57: 0 | AG57: 0 | AH57: 255.96 | AI57: 570.51 | AJ57: Stayed | AK57: 0 | AL57: 0 | AM57: Yes | AN57: No
A58: 0096-FCPUF | B58: Male | C58: 58 | D58: No | E58: 0 | F58: Santa Rosa | G58: 95404 | H58: 38.526941 | I58: -122.7091 | J58: 0 | K58: 30 | L58: 0 | M58: Yes | N58: 2.64 | O58: Yes | P58: Yes | Q58: DSL | R58: 15 | S58: Yes | T58: No | U58: No | V58: No | W58: No | X58: Yes | Y58: Yes | Z58: Yes | AA58: Month-to-Month | AB58: Yes | AC58: Mailed Check | AD58: 64.5 | AE58: 1888.45 | AF58: 0 | AG58: 0 | AH58: 79.2 | AI58: 1967.65 | AJ58: Stayed | AK58: 0 | AL58: 0 | AM58: Yes | AN58: Yes
A59: 0098-BOWSO | B59: Male | C59: 26 | D59: No | E59: 0 | F59: San Jose | G59: 95131 | H59: 37.387027 | I59: -121.89777 | J59: 0 | K59: 27 | L59: 0 | M59: Yes | N59: 20.66 | O59: No | P59: No | Q59: 0 | R59: 0 | S59: 0 | T59: 0 | U59: 0 | V59: 0 | W59: 0 | X59: 0 | Y59: 0 | Z59: 0 | AA59: Month-to-Month | AB59: Yes | AC59: Bank Withdrawal | AD59: 19.4 | AE59: 529.8 | AF59: 0 | AG59: 0 | AH59: 557.82 | AI59: 1087.62 | AJ59: Stayed | AK59: 0 | AL59: 0 | AM59: No | AN59: 0
A60: 0100-DUVFC | B60: Male | C60: 66 | D60: Yes | E60: 0 | F60: Wilmington | G60: 90744 | H60: 33.782068 | I60: -118.26226 | J60: 3 | K60: 70 | L60: 0 | M60: Yes | N60: 39.49 | O60: Yes | P60: Yes | Q60: Fiber Optic | R60: 28 | S60: No | T60: Yes | U60: Yes | V60: No | W60: Yes | X60: Yes | Y60: No | Z60: Yes | AA60: One Year | AB60: Yes | AC60: Bank Withdrawal | AD60: 104.8 | AE60: 7308.95 | AF60: 6.11 | AG60: 0 | AH60: 2764.3 | AI60: 10067.14 | AJ60: Stayed | AK60: 0 | AL60: 0 | AM60: Yes | AN60: No
A61: 0103-CSITQ | B61: Female | C61: 20 | D61: Yes | E61: 0 | F61: Modesto | G61: 95357 | H61: 37.670526 | I61: -120.87757 | J61: 10 | K61: 57 | L61: Offer B | M61: Yes | N61: 8.01 | O61: Yes | P61: Yes | Q61: Fiber Optic | R61: 73 | S61: No | T61: Yes | U61: Yes | V61: Yes | W61: Yes | X61: Yes | Y61: Yes | Z61: Yes | AA61: One Year | AB61: Yes | AC61: Bank Withdrawal | AD61: 109.4 | AE61: 6252.7 | AF61: 0 | AG61: 0 | AH61: 456.57 | AI61: 6709.27 | AJ61: Stayed | AK61: 0 | AL61: 0 | AM61: Yes | AN61: No
A62: 0104-PPXDV | B62: Male | C62: 61 | D62: Yes | E62: 0 | F62: San Diego | G62: 92113 | H62: 32.697098 | I62: -117.11659 | J62: 10 | K62: 58 | L62: 0 | M62: Yes | N62: 18.37 | O62: No | P62: Yes | Q62: DSL | R62: 18 | S62: No | T62: No | U62: Yes | V62: No | W62: No | X62: No | Y62: No | Z62: Yes | AA62: One Year | AB62: No | AC62: Credit Card | AD62: 50.3 | AE62: 2878.55 | AF62: 10.23 | AG62: 0 | AH62: 1065.46 | AI62: 3933.78 | AJ62: Stayed | AK62: 0 | AL62: 0 | AM62: No | AN62: No
A63: 0106-GHRQR | B63: Male | C63: 24 | D63: No | E63: 0 | F63: Rancho Palos Verdes | G63: 90275 | H63: 33.753146 | I63: -118.36746 | J63: 0 | K63: 16 | L63: 0 | M63: Yes | N63: 25.71 | O63: Yes | P63: Yes | Q63: DSL | R63: 48 | S63: No | T63: Yes | U63: Yes | V63: No | W63: No | X63: Yes | Y63: Yes | Z63: Yes | AA63: Month-to-Month | AB63: Yes | AC63: Bank Withdrawal | AD63: 71.4 | AE63: 1212.1 | AF63: 0 | AG63: 0 | AH63: 411.36 | AI63: 1623.46 | AJ63: Stayed | AK63: 0 | AL63: 0 | AM63: Yes | AN63: No
A64: 0106-UGRDO | B64: Female | C64: 55 | D64: Yes | E64: 0 | F64: Kenwood | G64: 95452 | H64: 38.419525 | I64: -122.52159 | J64: 3 | K64: 69 | L64: Offer A | M64: Yes | N64: 38.52 | O64: Yes | P64: Yes | Q64: Fiber Optic | R64: 27 | S64: Yes | T64: Yes | U64: Yes | V64: Yes | W64: Yes | X64: Yes | Y64: Yes | Z64: Yes | AA64: Two Year | AB64: Yes | AC64: Bank Withdrawal | AD64: 116 | AE64: 8182.85 | AF64: 0 | AG64: 0 | AH64: 2657.88 | AI64: 10840.73 | AJ64: Stayed | AK64: 0 | AL64: 0 | AM64: Yes | AN64: Yes
A65: 0107-WESLM | B65: Male | C65: 32 | D65: No | E65: 0 | F65: West Point | G65: 95255 | H65: 38.41935 | I65: -120.46954 | J65: 0 | K65: 1 | L65: Offer E | M65: Yes | N65: 31.77 | O65: No | P65: No | Q65: 0 | R65: 0 | S65: 0 | T65: 0 | U65: 0 | V65: 0 | W65: 0 | X65: 0 | Y65: 0 | Z65: 0 | AA65: Month-to-Month | AB65: Yes | AC65: Bank Withdrawal | AD65: 19.85 | AE65: 19.85 | AF65: 0 | AG65: 0 | AH65: 31.77 | AI65: 51.62 | AJ65: Churned | AK65: Attitude | AL65: Attitude of support person | AM65: No | AN65: 0
A66: 0107-YHINA | B66: Male | C66: 59 | D66: No | E66: 0 | F66: Los Angeles | G66: 90062 | H66: 34.003553 | I66: -118.30893 | J66: 0 | K66: 1 | L66: 0 | M66: Yes | N66: 40.71 | O66: Yes | P66: Yes | Q66: Fiber Optic | R66: 25 | S66: No | T66: No | U66: Yes | V66: No | W66: Yes | X66: Yes | Y66: Yes | Z66: Yes | AA66: Month-to-Month | AB66: Yes | AC66: Bank Withdrawal | AD66: 99.75 | AE66: 99.75 | AF66: 0 | AG66: 0 | AH66: 40.71 | AI66: 140.46 | AJ66: Churned | AK66: Competitor | AL66: Competitor had better devices | AM66: Yes | AN66: No
A67: 0111-KLBQG | B67: Male | C67: 71 | D67: Yes | E67: 1 | F67: Morongo Valley | G67: 92256 | H67: 34.097863 | I67: -116.59456 | J67: 9 | K67: 32 | L67: Offer C | M67: Yes | N67: 31.86 | O67: No | P67: Yes | Q67: Fiber Optic | R67: 23 | S67: No | T67: Yes | U67: No | V67: No | W67: Yes | X67: Yes | Y67: Yes | Z67: Yes | AA67: One Year | AB67: Yes | AC67: Mailed Check | AD67: 93.95 | AE67: 2861.45 | AF67: 0 | AG67: 0 | AH67: 1019.52 | AI67: 3880.97 | AJ67: Stayed | AK67: 0 | AL67: 0 | AM67: No | AN67: No
A68: 0112-QAWRZ | B68: Male | C68: 49 | D68: Yes | E68: 2 | F68: Palo Verde | G68: 92266 | H68: 33.3249 | I68: -114.75833 | J68: 8 | K68: 16 | L68: Offer D | M68: Yes | N68: 48.71 | O68: Yes | P68: Yes | Q68: Fiber Optic | R68: 12 | S68: No | T68: No | U68: Yes | V68: No | W68: Yes | X68: No | Y68: No | Z68: Yes | AA68: Month-to-Month | AB68: Yes | AC68: Bank Withdrawal | AD68: 90.8 | AE68: 1442.2 | AF68: 0 | AG68: 0 | AH68: 779.36 | AI68: 2221.56 | AJ68: Stayed | AK68: 0 | AL68: 0 | AM68: Yes | AN68: No
A69: 0112-QWPNC | B69: Male | C69: 61 | D69: Yes | E69: 0 | F69: Valyermo | G69: 93563 | H69: 34.39583 | I69: -117.73457 | J69: 1 | K69: 49 | L69: Offer B | M69: Yes | N69: 39.55 | O69: Yes | P69: Yes | Q69: Cable | R69: 10 | S69: Yes | T69: No | U69: Yes | V69: Yes | W69: Yes | X69: Yes | Y69: Yes | Z69: Yes | AA69: One Year | AB69: No | AC69: Bank Withdrawal | AD69: 84.35 | AE69: 4059.35 | AF69: 0 | AG69: 0 | AH69: 1937.95 | AI69: 5997.3 | AJ69: Churned | AK69: Competitor | AL69: Competitor offered higher download speeds | AM69: Yes | AN69: Yes
A70: 0114-IGABW | B70: Female | C70: 40 | D70: Yes | E70: 0 | F70: Cambria | G70: 93428 | H70: 35.591387 | I70: -121.03226 | J70: 2 | K70: 71 | L70: Offer A | M70: No | N70: 0 | O70: 0 | P70: Yes | Q70: Cable | R70: 29 | S70: No | T70: Yes | U70: Yes | V70: Yes | W70: Yes | X70: Yes | Y70: Yes | Z70: Yes | AA70: Two Year | AB70: No | AC70: Bank Withdrawal | AD70: 58.25 | AE70: 4145.9 | AF70: 0 | AG70: 0 | AH70: 0 | AI70: 4145.9 | AJ70: Stayed | AK70: 0 | AL70: 0 | AM70: 0 | AN70: No
A71: 0114-PEGZZ | B71: Female | C71: 39 | D71: No | E71: 0 | F71: Round Mountain | G71: 96084 | H71: 40.923558 | I71: -122.05993 | J71: 0 | K71: 33 | L71: 0 | M71: Yes | N71: 49.69 | O71: Yes | P71: Yes | Q71: Fiber Optic | R71: 12 | S71: No | T71: Yes | U71: Yes | V71: No | W71: Yes | X71: Yes | Y71: Yes | Z71: Yes | AA71: Month-to-Month | AB71: No | AC71: Bank Withdrawal | AD71: 107.55 | AE71: 3645.5 | AF71: 0 | AG71: 0 | AH71: 1639.77 | AI71: 5285.27 | AJ71: Stayed | AK71: 0 | AL71: 0 | AM71: Yes | AN71: No
A72: 0114-RSRRW | B72: Female | C72: 21 | D72: Yes | E72: 0 | F72: Klamath | G72: 95548 | H72: 41.572813 | I72: -124.03501 | J72: 9 | K72: 10 | L72: Offer D | M72: Yes | N72: 49.6 | O72: No | P72: No | Q72: 0 | R72: 0 | S72: 0 | T72: 0 | U72: 0 | V72: 0 | W72: 0 | X72: 0 | Y72: 0 | Z72: 0 | AA72: Month-to-Month | AB72: Yes | AC72: Bank Withdrawal | AD72: 19.95 | AE72: 187.75 | AF72: 0 | AG72: 0 | AH72: 496 | AI72: 683.75 | AJ72: Stayed | AK72: 0 | AL72: 0 | AM72: No | AN72: 0
A73: 0115-TFERT | B73: Male | C73: 24 | D73: Yes | E73: 0 | F73: Fresno | G73: 93650 | H73: 36.841655 | I73: -119.79711 | J73: 1 | K73: 21 | L73: 0 | M73: Yes | N73: 36.26 | O73: Yes | P73: Yes | Q73: Fiber Optic | R73: 59 | S73: No | T73: Yes | U73: Yes | V73: Yes | W73: Yes | X73: Yes | Y73: Yes | Z73: No | AA73: Month-to-Month | AB73: Yes | AC73: Bank Withdrawal | AD73: 111.2 | AE73: 2317.1 | AF73: 0 | AG73: 120 | AH73: 761.46 | AI73: 3198.56 | AJ73: Churned | AK73: Attitude | AL73: Attitude of service provider | AM73: Yes | AN73: No
A74: 0117-LFRMW | B74: Male | C74: 52 | D74: Yes | E74: 1 | F74: Angwin | G74: 94508 | H74: 38.542448 | I74: -122.41992 | J74: 1 | K74: 37 | L74: 0 | M74: No | N74: 0 | O74: 0 | P74: Yes | Q74: DSL | R74: 23 | S74: Yes | T74: Yes | U74: Yes | V74: No | W74: No | X74: No | Y74: No | Z74: Yes | AA74: Month-to-Month | AB74: No | AC74: Bank Withdrawal | AD74: 40.2 | AE74: 1448.8 | AF74: 0 | AG74: 0 | AH74: 0 | AI74: 1448.8 | AJ74: Churned | AK74: Competitor | AL74: Competitor offered more data | AM74: 0 | AN74: Yes
A75: 0118-JPNOY | B75: Female | C75: 71 | D75: No | E75: 0 | F75: Le Grand | G75: 95333 | H75: 37.249377 | I75: -120.24958 | J75: 0 | K75: 26 | L75: 0 | M75: Yes | N75: 33.74 | O75: No | P75: Yes | Q75: Fiber Optic | R75: 7 | S75: Yes | T75: No | U75: No | V75: No | W75: Yes | X75: No | Y75: No | Z75: Yes | AA75: Month-to-Month | AB75: Yes | AC75: Credit Card | AD75: 85.8 | AE75: 2193.65 | AF75: 0 | AG75: 0 | AH75: 877.24 | AI75: 3070.89 | AJ75: Stayed | AK75: 0 | AL75: 0 | AM75: No | AN75: Yes
A76: 0121-SNYRK | B76: Male | C76: 45 | D76: No | E76: 0 | F76: Redway | G76: 95560 | H76: 40.142256 | I76: -123.85293 | J76: 0 | K76: 50 | L76: Offer B | M76: No | N76: 0 | O76: 0 | P76: Yes | Q76: DSL | R76: 7 | S76: Yes | T76: No | U76: No | V76: Yes | W76: No | X76: No | Y76: No | Z76: Yes | AA76: One Year | AB76: Yes | AC76: Credit Card | AD76: 35.4 | AE76: 1748.9 | AF76: 0 | AG76: 0 | AH76: 0 | AI76: 1748.9 | AJ76: Stayed | AK76: 0 | AL76: 0 | AM76: 0 | AN76: Yes
A77: 0122-OAHPZ | B77: Female | C77: 29 | D77: No | E77: 0 | F77: San Diego | G77: 92122 | H77: 32.85723 | I77: -117.20977 | J77: 0 | K77: 7 | L77: 0 | M77: Yes | N77: 28.62 | O77: Yes | P77: Yes | Q77: Fiber Optic | R77: 26 | S77: No | T77: No | U77: No | V77: No | W77: No | X77: No | Y77: Yes | Z77: Yes | AA77: Month-to-Month | AB77: Yes | AC77: Bank Withdrawal | AD77: 73.85 | AE77: 511.25 | AF77: 13.03 | AG77: 0 | AH77: 200.34 | AI77: 698.56 | AJ77: Churned | AK77: Competitor | AL77: Competitor made better offer | AM77: Yes | AN77: No
A78: 0123-CRBRT | B78: Female | C78: 62 | D78: Yes | E78: 0 | F78: Monterey Park | G78: 91755 | H78: 34.049172 | I78: -118.11502 | J78: 1 | K78: 61 | L78: Offer B | M78: Yes | N78: 47.19 | O78: Yes | P78: Yes | Q78: DSL | R78: 28 | S78: Yes | T78: Yes | U78: Yes | V78: Yes | W78: Yes | X78: Yes | Y78: Yes | Z78: Yes | AA78: Two Year | AB78: No | AC78: Mailed Check | AD78: 88.1 | AE78: 5526.75 | AF78: 0 | AG78: 0 | AH78: 2878.59 | AI78: 8405.34 | AJ78: Stayed | AK78: 0 | AL78: 0 | AM78: Yes | AN78: Yes
A79: 0125-LZQXK | B79: Male | C79: 42 | D79: No | E79: 0 | F79: Big Oak Flat | G79: 95305 | H79: 37.818589 | I79: -120.257 | J79: 0 | K79: 15 | L79: Offer D | M79: Yes | N79: 45.92 | O79: No | P79: Yes | Q79: Fiber Optic | R79: 12 | S79: No | T79: No | U79: Yes | V79: Yes | W79: Yes | X79: Yes | Y79: Yes | Z79: Yes | AA79: Month-to-Month | AB79: Yes | AC79: Bank Withdrawal | AD79: 101.35 | AE79: 1553.95 | AF79: 0 | AG79: 0 | AH79: 688.8 | AI79: 2242.75 | AJ79: Churned | AK79: Attitude | AL79: Attitude of service provider | AM79: No | AN79: No
A80: 0128-MKWSG | B80: Female | C80: 51 | D80: No | E80: 2 | F80: Stevenson Ranch | G80: 91381 | H80: 34.364153 | I80: -118.61558 | J80: 0 | K80: 26 | L80: 0 | M80: No | N80: 0 | O80: 0 | P80: Yes | Q80: DSL | R80: 19 | S80: Yes | T80: No | U80: No | V80: Yes | W80: No | X80: Yes | Y80: Yes | Z80: Yes | AA80: Month-to-Month | AB80: No | AC80: Credit Card | AD80: 45.8 | AE80: 1147 | AF80: 0 | AG80: 0 | AH80: 0 | AI80: 1147 | AJ80: Stayed | AK80: 0 | AL80: 0 | AM80: 0 | AN80: Yes
A81: 0129-KPTWJ | B81: Male | C81: 39 | D81: Yes | E81: 0 | F81: North Highlands | G81: 95660 | H81: 38.671295 | I81: -121.38825 | J81: 9 | K81: 72 | L81: 0 | M81: Yes | N81: 33.22 | O81: No | P81: Yes | Q81: Fiber Optic | R81: 23 | S81: No | T81: No | U81: Yes | V81: No | W81: Yes | X81: Yes | Y81: Yes | Z81: Yes | AA81: Month-to-Month | AB81: Yes | AC81: Bank Withdrawal | AD81: 94.65 | AE81: 6747.35 | AF81: 0 | AG81: 0 | AH81: 2391.84 | AI81: 9139.19 | AJ81: Stayed | AK81: 0 | AL81: 0 | AM81: No | AN81: No
A82: 0129-QMPDR | B82: Male | C82: 64 | D82: Yes | E82: 0 | F82: La Puente | G82: 91746 | H82: 34.038983 | I82: -117.99137 | J82: 1 | K82: 44 | L82: 0 | M82: Yes | N82: 27.4 | O82: No | P82: No | Q82: 0 | R82: 0 | S82: 0 | T82: 0 | U82: 0 | V82: 0 | W82: 0 | X82: 0 | Y82: 0 | Z82: 0 | AA82: One Year | AB82: Yes | AC82: Bank Withdrawal | AD82: 20.5 | AE82: 865.05 | AF82: 0 | AG82: 0 | AH82: 1205.6 | AI82: 2070.65 | AJ82: Stayed | AK82: 0 | AL82: 0 | AM82: No | AN82: 0
A83: 0130-SXOUN | B83: Male | C83: 55 | D83: No | E83: 0 | F83: Glenhaven | G83: 95443 | H83: 39.045246 | I83: -122.74318 | J83: 0 | K83: 66 | L83: Offer A | M83: Yes | N83: 48.78 | O83: Yes | P83: Yes | Q83: Fiber Optic | R83: 8 | S83: No | T83: Yes | U83: No | V83: No | W83: No | X83: Yes | Y83: Yes | Z83: No | AA83: Month-to-Month | AB83: No | AC83: Credit Card | AD83: 89.4 | AE83: 5976.9 | AF83: 36.02 | AG83: 40 | AH83: 3219.48 | AI83: 9200.36 | AJ83: Stayed | AK83: 0 | AL83: 0 | AM83: Yes | AN83: No
A84: 0133-BMFZO | B84: Female | C84: 40 | D84: No | E84: 0 | F84: Alhambra | G84: 91803 | H84: 34.074736 | I84: -118.14596 | J84: 0 | K84: 2 | L84: 0 | M84: Yes | N84: 36.81 | O84: No | P84: Yes | Q84: Fiber Optic | R84: 16 | S84: Yes | T84: Yes | U84: No | V84: Yes | W84: No | X84: No | Y84: No | Z84: Yes | AA84: Month-to-Month | AB84: Yes | AC84: Bank Withdrawal | AD84: 86.25 | AE84: 181.65 | AF84: 0 | AG84: 0 | AH84: 73.62 | AI84: 255.27 | AJ84: Churned | AK84: Competitor | AL84: Competitor offered higher download speeds | AM84: No | AN84: Yes
A85: 0134-XWXCE | B85: Female | C85: 76 | D85: No | E85: 0 | F85: Santa Monica | G85: 90403 | H85: 34.031529 | I85: -118.49116 | J85: 0 | K85: 44 | L85: 0 | M85: Yes | N85: 7.72 | O85: No | P85: Yes | Q85: DSL | R85: 17 | S85: No | T85: No | U85: Yes | V85: Yes | W85: Yes | X85: Yes | Y85: Yes | Z85: Yes | AA85: One Year | AB85: No | AC85: Bank Withdrawal | AD85: 74.85 | AE85: 3268.05 | AF85: 17.91 | AG85: 0 | AH85: 339.68 | AI85: 3589.82 | AJ85: Stayed | AK85: 0 | AL85: 0 | AM85: No | AN85: No
A86: 0135-NMXAP | B86: Female | C86: 57 | D86: No | E86: 0 | F86: Lodi | G86: 95240 | H86: 38.123544 | I86: -121.15908 | J86: 0 | K86: 12 | L86: Offer D | M86: Yes | N86: 14.38 | O86: Yes | P86: Yes | Q86: Fiber Optic | R86: 6 | S86: No | T86: Yes | U86: No | V86: No | W86: Yes | X86: No | Y86: No | Z86: Yes | AA86: Month-to-Month | AB86: Yes | AC86: Bank Withdrawal | AD86: 89.75 | AE86: 1052.4 | AF86: 0 | AG86: 0 | AH86: 172.56 | AI86: 1224.96 | AJ86: Churned | AK86: Attitude | AL86: Attitude of support person | AM86: Yes | AN86: No
A87: 0136-IFMYD | B87: Male | C87: 71 | D87: Yes | E87: 0 | F87: Los Angeles | G87: 90001 | H87: 33.973616 | I87: -118.24902 | J87: 1 | K87: 69 | L87: 0 | M87: Yes | N87: 18.41 | O87: Yes | P87: Yes | Q87: Fiber Optic | R87: 17 | S87: No | T87: Yes | U87: Yes | V87: Yes | W87: Yes | X87: Yes | Y87: No | Z87: Yes | AA87: Two Year | AB87: Yes | AC87: Bank Withdrawal | AD87: 109.95 | AE87: 7634.25 | AF87: 0 | AG87: 0 | AH87: 1270.29 | AI87: 8904.54 | AJ87: Stayed | AK87: 0 | AL87: 0 | AM87: Yes | AN87: No
A88: 0137-OCGAB | B88: Female | C88: 25 | D88: No | E88: 0 | F88: Fairfield | G88: 94533 | H88: 38.287136 | I88: -122.02711 | J88: 0 | K88: 1 | L88: Offer E | M88: Yes | N88: 1.23 | O88: Yes | P88: Yes | Q88: Fiber Optic | R88: 69 | S88: No | T88: Yes | U88: No | V88: No | W88: No | X88: No | Y88: No | Z88: Yes | AA88: Month-to-Month | AB88: Yes | AC88: Mailed Check | AD88: 80.2 | AE88: 80.2 | AF88: 0 | AG88: 0 | AH88: 1.23 | AI88: 81.43 | AJ88: Churned | AK88: Price | AL88: Lack of affordable download/upload speed | AM88: Yes | AN88: No
A89: 0137-UDEUO | B89: Female | C89: 24 | D89: No | E89: 0 | F89: Stockton | G89: 95204 | H89: 37.974498 | I89: -121.31957 | J89: 0 | K89: 3 | L89: Offer E | M89: Yes | N89: 25.75 | O89: No | P89: No | Q89: 0 | R89: 0 | S89: 0 | T89: 0 | U89: 0 | V89: 0 | W89: 0 | X89: 0 | Y89: 0 | Z89: 0 | AA89: Month-to-Month | AB89: No | AC89: Credit Card | AD89: 19.85 | AE89: 63.75 | AF89: 0 | AG89: 0 | AH89: 77.25 | AI89: 141 | AJ89: Churned | AK89: Price | AL89: Long distance charges | AM89: No | AN89: 0
A90: 0139-IVFJG | B90: Female | C90: 19 | D90: Yes | E90: 0 | F90: Temecula | G90: 92592 | H90: 33.507255 | I90: -117.02947 | J90: 10 | K90: 2 | L90: 0 | M90: Yes | N90: 4.65 | O90: No | P90: Yes | Q90: Fiber Optic | R90: 53 | S90: Yes | T90: Yes | U90: No | V90: No | W90: Yes | X90: No | Y90: No | Z90: Yes | AA90: Month-to-Month | AB90: No | AC90: Bank Withdrawal | AD90: 90.35 | AE90: 190.5 | AF90: 0 | AG90: 0 | AH90: 9.3 | AI90: 199.8 | AJ90: Joined | AK90: 0 | AL90: 0 | AM90: No | AN90: Yes
A91: 0141-YEAYS | B91: Female | C91: 77 | D91: No | E91: 0 | F91: Fallbrook | G91: 92028 | H91: 33.362575 | I91: -117.29964 | J91: 0 | K91: 27 | L91: 0 | M91: Yes | N91: 2.97 | O91: Yes | P91: Yes | Q91: Fiber Optic | R91: 4 | S91: No | T91: Yes | U91: Yes | V91: No | W91: No | X91: No | Y91: No | Z91: Yes | AA91: Two Year | AB91: Yes | AC91: Bank Withdrawal | AD91: 86.45 | AE91: 2401.05 | AF91: 0 | AG91: 0 | AH91: 80.19 | AI91: 2481.24 | AJ91: Stayed | AK91: 0 | AL91: 0 | AM91: Yes | AN91: No
A92: 0142-GVYSN | B92: Male | C92: 57 | D92: No | E92: 0 | F92: Randsburg | G92: 93554 | H92: 35.405722 | I92: -117.77335 | J92: 0 | K92: 26 | L92: Offer C | M92: Yes | N92: 13.34 | O92: No | P92: No | Q92: 0 | R92: 0 | S92: 0 | T92: 0 | U92: 0 | V92: 0 | W92: 0 | X92: 0 | Y92: 0 | Z92: 0 | AA92: Month-to-Month | AB92: Yes | AC92: Bank Withdrawal | AD92: 20.3 | AE92: 511.25 | AF92: 0 | AG92: 0 | AH92: 346.84 | AI92: 858.09 | AJ92: Stayed | AK92: 0 | AL92: 0 | AM92: No | AN92: 0
A93: 0147-ESWWR | B93: Female | C93: 73 | D93: Yes | E93: 0 | F93: Atascadero | G93: 93422 | H93: 35.453912 | I93: -120.69461 | J93: 9 | K93: 39 | L93: 0 | M93: Yes | N93: 20.15 | O93: Yes | P93: Yes | Q93: Fiber Optic | R93: 21 | S93: No | T93: No | U93: No | V93: Yes | W93: Yes | X93: Yes | Y93: Yes | Z93: Yes | AA93: Month-to-Month | AB93: Yes | AC93: Bank Withdrawal | AD93: 101.25 | AE93: 3949.15 | AF93: 0 | AG93: 0 | AH93: 785.85 | AI93: 4735 | AJ93: Stayed | AK93: 0 | AL93: 0 | AM93: Yes | AN93: No
A94: 0148-DCDOS | B94: Male | C94: 41 | D94: No | E94: 0 | F94: Planada | G94: 95365 | H94: 37.329725 | I94: -120.3064 | J94: 0 | K94: 25 | L94: 0 | M94: Yes | N94: 34.88 | O94: Yes | P94: Yes | Q94: Fiber Optic | R94: 8 | S94: No | T94: No | U94: No | V94: No | W94: Yes | X94: Yes | Y94: Yes | Z94: Yes | AA94: Month-to-Month | AB94: Yes | AC94: Bank Withdrawal | AD94: 94.7 | AE94: 2362.1 | AF94: 0 | AG94: 0 | AH94: 872 | AI94: 3234.1 | AJ94: Churned | AK94: Competitor | AL94: Competitor had better devices | AM94: Yes | AN94: No
A95: 0151-ONTOV | B95: Female | C95: 43 | D95: No | E95: 0 | F95: Moorpark | G95: 93021 | H95: 34.312945 | I95: -118.85817 | J95: 0 | K95: 1 | L95: Offer E | M95: Yes | N95: 39.81 | O95: No | P95: Yes | Q95: Fiber Optic | R95: 23 | S95: No | T95: No | U95: No | V95: No | W95: No | X95: No | Y95: No | Z95: Yes | AA95: Month-to-Month | AB95: No | AC95: Mailed Check | AD95: 70.9 | AE95: 70.9 | AF95: 0 | AG95: 0 | AH95: 39.81 | AI95: 110.71 | AJ95: Churned | AK95: Competitor | AL95: Competitor had better devices | AM95: No | AN95: No
A96: 0156-FVPTA | B96: Male | C96: 48 | D96: Yes | E96: 0 | F96: Solvang | G96: 93463 | H96: 34.624399 | I96: -120.13787 | J96: 1 | K96: 22 | L96: Offer D | M96: Yes | N96: 27.24 | O96: No | P96: Yes | Q96: DSL | R96: 21 | S96: Yes | T96: No | U96: No | V96: Yes | W96: No | X96: No | Y96: No | Z96: Yes | AA96: Month-to-Month | AB96: Yes | AC96: Bank Withdrawal | AD96: 54.2 | AE96: 1152.7 | AF96: 0 | AG96: 0 | AH96: 599.28 | AI96: 1751.98 | AJ96: Churned | AK96: Attitude | AL96: Attitude of service provider | AM96: No | AN96: Yes
A97: 0164-APGRB | B97: Female | C97: 56 | D97: No | E97: 0 | F97: Calistoga | G97: 94515 | H97: 38.629618 | I97: -122.59322 | J97: 0 | K97: 72 | L97: Offer A | M97: Yes | N97: 48.37 | O97: Yes | P97: Yes | Q97: Fiber Optic | R97: 5 | S97: Yes | T97: Yes | U97: Yes | V97: Yes | W97: Yes | X97: Yes | Y97: Yes | Z97: Yes | AA97: Two Year | AB97: Yes | AC97: Bank Withdrawal | AD97: 114.9 | AE97: 8496.7 | AF97: 0 | AG97: 0 | AH97: 3482.64 | AI97: 11979.34 | AJ97: Stayed | AK97: 0 | AL97: 0 | AM97: Yes | AN97: Yes
A98: 0164-XAIRP | B98: Female | C98: 51 | D98: No | E98: 0 | F98: La Mirada | G98: 90638 | H98: 33.902045 | I98: -118.00896 | J98: 0 | K98: 24 | L98: 0 | M98: Yes | N98: 10.64 | O98: No | P98: No | Q98: 0 | R98: 0 | S98: 0 | T98: 0 | U98: 0 | V98: 0 | W98: 0 | X98: 0 | Y98: 0 | Z98: 0 | AA98: Two Year | AB98: Yes | AC98: Bank Withdrawal | AD98: 19.55 | AE98: 470.2 | AF98: 0 | AG98: 0 | AH98: 255.36 | AI98: 725.56 | AJ98: Stayed | AK98: 0 | AL98: 0 | AM98: No | AN98: 0
A99: 0168-XZKBB | B99: Female | C99: 34 | D99: Yes | E99: 0 | F99: Boron | G99: 93516 | H99: 34.95703 | I99: -117.73045 | J99: 8 | K99: 19 | L99: 0 | M99: Yes | N99: 7.84 | O99: Yes | P99: Yes | Q99: Fiber Optic | R99: 16 | S99: No | T99: No | U99: No | V99: No | W99: Yes | X99: No | Y99: No | Z99: Yes | AA99: Month-to-Month | AB99: Yes | AC99: Bank Withdrawal | AD99: 86.85 | AE99: 1564.4 | AF99: 0 | AG99: 0 | AH99: 148.96 | AI99: 1713.36 | AJ99: Stayed | AK99: 0 | AL99: 0 | AM99: Yes | AN99: No
A100: 0174-QRVVY | B100: Male | C100: 21 | D100: Yes | E100: 2 | F100: San Marcos | G100: 92078 | H100: 33.119028 | I100: -117.16604 | J100: 2 | K100: 71 | L100: 0 | M100: Yes | N100: 9.2 | O100: Yes | P100: No | Q100: 0 | R100: 0 | S100: 0 | T100: 0 | U100: 0 | V100: 0 | W100: 0 | X100: 0 | Y100: 0 | Z100: 0 | AA100: Two Year | AB100: No | AC100: Credit Card | AD100: 25.35 | AE100: 1847.55 | AF100: 0 | AG100: 0 | AH100: 653.2 | AI100: 2500.75 | AJ100: Stayed | AK100: 0 | AL100: 0 | AM100: Yes | AN100: 0
...

Sheet Analysis
D2: Telecom Churn Customers Analysis
A8: Total Customers | C8: =COUNTA(Table1[customer_id]) -> 7043 | E8: Churned Customers | G8: =COUNTIF(Table1[[#All],[customer_status]],"Churned") -> 1869 | I8: Churn Rate | K8: =G8/C8 -> 0.26536987
A11: Stayed Customers | C11: =COUNTIF(Table1[[#All],[customer_status]],"Stayed") -> 4720 | E11: Joined Customers | G11: =COUNTIF(Table1[[#All],[customer_status]],"Joined") -> 454 | I11: Total Revenue | K11: =SUM(Table1[[#All],[total_charges]]) -> 16060725
A15: 1. Contract Performance
A16: Contract | B16: Customers | C16: Churned | D16: Churn Rate | F16: Variance
A17: Month-to-Month | B17: =COUNTIF(Table1[[#All],[contract]],Analysis!A17) -> 3610 | C17: =COUNTIFS(Table1[[#All],[contract]],Analysis!A17,Table1[[#All],[customer_status]],"Churned") -> 1655 | D17: =IFERROR(C17/B17,0) -> 0.45844875
A18: One Year | B18: =COUNTIF(Table1[[#All],[contract]],Analysis!A18) -> 1550 | C18: =COUNTIFS(Table1[[#All],[contract]],Analysis!A18,Table1[[#All],[customer_status]],"Churned") -> 166 | D18: =IFERROR(C18/B18,0) -> 0.10709677
A19: Two Year | B19: =COUNTIF(Table1[[#All],[contract]],Analysis!A19) -> 1883 | C19: =COUNTIFS(Table1[[#All],[contract]],Analysis!A19,Table1[[#All],[customer_status]],"Churned") -> 48 | D19: =IFERROR(C19/B19,0) -> 0.025491237
A22: 2. Internet Type Churn Analysis
A23: Internet Type | B23: Customers | C23: Churned | D23: Churn Rate | E23: Avg Monthly Charge | F23: Total Revenue
A24: 0 | B24: =COUNTIF(Table1[[#All],[internet_type]],Analysis!A24) -> 1526 | C24: =COUNTIFS(Table1[[#All],[internet_type]],Analysis!A24,Table1[[#All],[customer_status]],"Churned") -> 113 | D24: =C24/B24 -> 0.074049803 | E24: =AVERAGEIF(Table1[internet_type],Analysis!A24,Table1[monthly_charge]) -> 20.613925 | F24: =SUMIF(Table1[[#All],[internet_type]],Analysis!A24,Table1[[#All],[total_revenue]]) -> 2185293.5
A25: Cable | B25: =COUNTIF(Table1[[#All],[internet_type]],Analysis!A25) -> 830 | C25: =COUNTIFS(Table1[[#All],[internet_type]],Analysis!A25,Table1[[#All],[customer_status]],"Churned") -> 213 | D25: =C25/B25 -> 0.25662651 | E25: =AVERAGEIF(Table1[internet_type],Analysis!A25,Table1[monthly_charge]) -> 59.355361 | F25: =SUMIF(Table1[[#All],[internet_type]],Analysis!A25,Table1[[#All],[total_revenue]]) -> 2228474.2
A26: DSL | B26: =COUNTIF(Table1[[#All],[internet_type]],Analysis!A26) -> 1652 | C26: =COUNTIFS(Table1[[#All],[internet_type]],Analysis!A26,Table1[[#All],[customer_status]],"Churned") -> 307 | D26: =C26/B26 -> 0.18583535 | E26: =AVERAGEIF(Table1[internet_type],Analysis!A26,Table1[monthly_charge]) -> 56.792494 | F26: =SUMIF(Table1[[#All],[internet_type]],Analysis!A26,Table1[[#All],[total_revenue]]) -> 4549289.6
A27: Fiber Optic | B27: =COUNTIF(Table1[[#All],[internet_type]],Analysis!A27) -> 3035 | C27: =COUNTIFS(Table1[[#All],[internet_type]],Analysis!A27,Table1[[#All],[customer_status]],"Churned") -> 1236 | D27: =C27/B27 -> 0.40724876 | E27: =AVERAGEIF(Table1[internet_type],Analysis!A27,Table1[monthly_charge]) -> 90.070692 | F27: =SUMIF(Table1[[#All],[internet_type]],Analysis!A27,Table1[[#All],[total_revenue]]) -> 12408074
A30: 3. Tenure Group Analysis
A31: Tenure Group | B31: Customers | C31: Churned | D31: Churn Rate
A32: 0-12 Months | B32: =COUNTIFS(Table1[tenure_in_months],">=0",Table1[tenure_in_months],"<=12") -> 2186 | C32: =COUNTIFS(Table1[tenure_in_months],">=0",Table1[tenure_in_months],"<=12",Table1[customer_status],"Churned") -> 1037 | D32: =C32/B32 -> 0.47438243
A33: 13-24 Months | B33: =COUNTIFS(Table1[[#All],[tenure_in_months]],">=12",Table1[[#All],[tenure_in_months]],"<=24") -> 1141 | C33: =COUNTIFS(Table1[tenure_in_months],">=12",Table1[tenure_in_months],"<=24",Table1[customer_status],"Churned") -> 332 | D33: =C33/B33 -> 0.29097283
A34: 25-48 Months | B34: =COUNTIFS(Table1[[#All],[tenure_in_months]],">=24",Table1[[#All],[tenure_in_months]],"<=48") -> 1688 | C34: =COUNTIFS(Table1[tenure_in_months],">=24",Table1[tenure_in_months],"<=48",Table1[customer_status],"Churned") -> 348 | D34: =C34/B34 -> 0.20616114
A35: 49-72 Months | B35: =COUNTIFS(Table1[[#All],[tenure_in_months]],">=48",Table1[[#All],[tenure_in_months]],"<=72") -> 2303 | C35: =COUNTIFS(Table1[tenure_in_months],">=48",Table1[tenure_in_months],"<=72",Table1[customer_status],"Churned") -> 222 | D35: =C35/B35 -> 0.096396005
A36: 72+ Months | B36: =COUNTIF(Table1[[#All],[tenure_in_months]],">=72") -> 362 | C36: =COUNTIFS(Table1[tenure_in_months],">=72",Table1[customer_status],"Churned") -> 6 | D36: =C36/B36 -> 0.016574586
A39: 4. Churn Reason Analysis
A40: Churn Reason | B40: Churned Customers | C40: Revenue Lost
A41: Attitude of service provider | B41: =COUNTIFS(Table1[churn_reason],Analysis!A41,Table1[customer_status],"Churned") -> 94 | C41: =SUMIFS(Table1[total_revenue],Table1[churn_reason],Analysis!A41,Table1[customer_status],"Churned") -> 174858.74
A42: Attitude of support person | B42: =COUNTIFS(Table1[churn_reason],Analysis!A42,Table1[customer_status],"Churned") -> 220 | C42: =SUMIFS(Table1[total_revenue],Table1[churn_reason],Analysis!A42,Table1[customer_status],"Churned") -> 404695.39
A43: Competitor had better devices | B43: =COUNTIFS(Table1[churn_reason],Analysis!A43,Table1[customer_status],"Churned") -> 313 | C43: =SUMIFS(Table1[total_revenue],Table1[churn_reason],Analysis!A43,Table1[customer_status],"Churned") -> 579877.05
A44: Competitor made better offer | B44: =COUNTIFS(Table1[churn_reason],Analysis!A44,Table1[customer_status],"Churned") -> 311 | C44: =SUMIFS(Table1[total_revenue],Table1[churn_reason],Analysis!A44,Table1[customer_status],"Churned") -> 582822.2
A45: Competitor offered higher download speeds | B45: =COUNTIFS(Table1[churn_reason],Analysis!A45,Table1[customer_status],"Churned") -> 100 | C45: =SUMIFS(Table1[total_revenue],Table1[churn_reason],Analysis!A45,Table1[customer_status],"Churned") -> 234145.69
A46: Competitor offered more data | B46: =COUNTIFS(Table1[churn_reason],Analysis!A46,Table1[customer_status],"Churned") -> 117 | C46: =SUMIFS(Table1[total_revenue],Table1[churn_reason],Analysis!A46,Table1[customer_status],"Churned") -> 297568.21
A47: Deceased | B47: =COUNTIFS(Table1[churn_reason],Analysis!A47,Table1[customer_status],"Churned") -> 6 | C47: =SUMIFS(Table1[total_revenue],Table1[churn_reason],Analysis!A47,Table1[customer_status],"Churned") -> 4172.83
A48: Don't know | B48: =COUNTIFS(Table1[churn_reason],Analysis!A48,Table1[customer_status],"Churned") -> 130 | C48: =SUMIFS(Table1[total_revenue],Table1[churn_reason],Analysis!A48,Table1[customer_status],"Churned") -> 256403.35
A49: Extra data charges | B49: =COUNTIFS(Table1[churn_reason],Analysis!A49,Table1[customer_status],"Churned") -> 39 | C49: =SUMIFS(Table1[total_revenue],Table1[churn_reason],Analysis!A49,Table1[customer_status],"Churned") -> 104152.72
A50: Lack of affordable download/upload speed | B50: =COUNTIFS(Table1[churn_reason],Analysis!A50,Table1[customer_status],"Churned") -> 30 | C50: =SUMIFS(Table1[total_revenue],Table1[churn_reason],Analysis!A50,Table1[customer_status],"Churned") -> 66772.76
A51: Lack of self-service on Website | B51: =COUNTIFS(Table1[churn_reason],Analysis!A51,Table1[customer_status],"Churned") -> 29 | C51: =SUMIFS(Table1[total_revenue],Table1[churn_reason],Analysis!A51,Table1[customer_status],"Churned") -> 36788.15
A52: Limited range of services | B52: =COUNTIFS(Table1[churn_reason],Analysis!A52,Table1[customer_status],"Churned") -> 37 | C52: =SUMIFS(Table1[total_revenue],Table1[churn_reason],Analysis!A52,Table1[customer_status],"Churned") -> 47254.43
... A60: Service dissatisfaction | B60: =COUNTIFS(Table1[churn_reason],Analysis!A60,Table1[customer_status],"Churned") -> 63 | C60: =SUMIFS(Table1[total_revenue],Table1[churn_reason],Analysis!A60,Table1[customer_status],"Churned") -> 122914.14
